xiaonie_mcp_demo/__init__.py
xiaonie_mcp_demo-0.1.0.dist-info/WHEEL
xiaonie_mcp_demo-0.1.0.dist-info/entry_points.txt
xiaonie_mcp_demo-0.1.0.dist-info/METADATA
xiaonie_mcp_demo-0.1.0.dist-info/RECORD
