Metadata-Version: 2.3
Name: xiaonie-mcp-demo
Version: 0.1.0
Summary: Add your description here
Requires-Dist: mcp[cli]>=1.23.1
Requires-Python: >=3.12
